fsion/__init__.py
fsion/backends/__init__.py
fsion/backends/drive.py
fsion/models/drive.py
fsion/models/fs/__init__.py
fsion/models/fs/backend.py
fsion-0.1.0a1.dist-info/METADATA
fsion-0.1.0a1.dist-info/WHEEL
fsion-0.1.0a1.dist-info/entry_points.txt
fsion-0.1.0a1.dist-info/licenses/LICENSE
fsion-0.1.0a1.dist-info/RECORD
